Metadata-Version: 2.1
Name: djnacos
Version: 3.0.0
Summary: A Django tool designed to simplify the usage of Nacos.
Home-page: https://github.com/lcoolcool/djnacos
Author: lcoolcool
Author-email: shuaishuai_zhai@163.com
Classifier: Programming Language :: Python :: 3
Classifier: License :: OSI Approved :: MIT License
Classifier: Operating System :: OS Independent
License-File: LICENSE
Requires-Dist: django>=2.2.0
Requires-Dist: nacos-sdk-python==1.0.0
